gendazpack/__init__.py
gendazpack/__main__.py
gendazpack/generator/__init__.py
gendazpack/generator/loadmetadata.py
gendazpack/generator/packagedata.py
gendazpack/generator/packagegenerator.py
gendazpack/scrapers/__init__.py
gendazpack/scrapers/cgtrader.py
gendazpack/scrapers/deviantart.py
gendazpack/scrapers/renderhub.py
gendazpack/scrapers/renderosity.py
gendazpack/scrapers/renderotica.py
gendazpack/scrapers/scraper.py
gendazpack/scrapers/sharecg.py
gendazpack-0.1.3.dist-info/entry_points.txt
gendazpack-0.1.3.dist-info/LICENSE
gendazpack-0.1.3.dist-info/METADATA
gendazpack-0.1.3.dist-info/WHEEL
gendazpack-0.1.3.dist-info/RECORD
