Metadata-Version: 2.1
Name: gendazpack
Version: 0.1.3
Summary: DAZ Content Package Generator
Home-page: https://github.com/Omniflux/gendazpack
License: MIT
Author: Omni Flux
Author-email: omniflux@omniflux.com
Requires-Python: >=3.11
Classifier: Development Status :: 5 - Production/Stable
Classifier: License :: OSI Approved :: MIT License
Classifier: Operating System :: OS Independent
Classifier: Programming Language :: Python :: 3
Classifier: Programming Language :: Python :: 3.11
Classifier: Programming Language :: Python :: 3.12
Classifier: Programming Language :: Python :: 3 :: Only
Classifier: Topic :: Utilities
Requires-Dist: Pillow (>=11.0.0,<12.0.0)
Requires-Dist: beautifulsoup4 (>=4.12.3,<5.0.0)
Requires-Dist: lxml (>=5.3.0,<6.0.0)
Requires-Dist: weasyprint (>=62.3,<63.0)
Project-URL: Repository, https://github.com/Omniflux/gendazpack
